httpeat.py
httpeat-0.4.dist-info/entry_points.txt
httpeat-0.4.dist-info/WHEEL
httpeat-0.4.dist-info/METADATA
httpeat-0.4.dist-info/RECORD
