Metadata-Version: 2.3
Name: httpeat
Version: 0.4
Summary: a recursive, parallel and multi-mirror/multi-proxy HTTP downloader
Keywords: http,downloader,recursive,parallel,mirror,proxy
Author-email: Laurent Ghigonis <ooookiwi@protonmail.com>
Requires-Python: >=3.0
Requires-Dist: httpx[socks]
Requires-Dist: bs4
Requires-Dist: lxml
Requires-Dist: python-dateutil
Requires-Dist: rich
Requires-Dist: humanfriendly
Requires-Dist: tenacity
Project-URL: Homepage, https://github.com/looran/httpeat
